{
  "$schema": "../../utils/game-info.schema.json",
  "gameCode": "E",
  "gameName": "esquiadores",
  "version": "0.1.0",
  "release": "dev",
  "available": true,
  "title": {
    "pt": "Esquiadores",
    "en": "Ski Resort"
  },
  "popularName": {
    "pt": "",
    "en": ""
  },
  "basedOn": "ammeliD thgiR tfeL",
  "summary": {
    "pt": "Jogadores apostam em o que o esquiador vai decidir em uma série de escolhas",
    "en": "Players bet on what the skier will decide in a series of choices"
  },
  "appearance": {
    "clouds": "cloud",
    "cloudsAnimationType": "falling",
    "primaryColor": "",
    "backgroundColor": "rgba(234, 235, 235, 0.95)",
    "colorScheme": "light"
  },
  "rules": {
    "pt": ["TBD"],
    "en": ["TBD"]
  },
  "playerCount": {
    "recommended": [4, 5, 6],
    "min": 2,
    "max": 10
  },
  "duration": {
    "base": 0,
    "perPlayer": 0
  },
  "tags": ["competitive", "same-time", "betting", "voting"],
  "options": [
    {
      "key": "nsfw",
      "kind": "switch",
      "label": "NSFW",
      "description": "Allow NSFW content",
      "values": [
        {
          "label": "Off",
          "value": false
        },
        {
          "label": "On",
          "value": true
        }
      ]
    }
  ]
}
